Workbook

Sheet Resumen
A1: 🌊 RESUMEN - VIAJE FAMILIAR A COVEÑAS
A2: Fechas | B2: 29 dic 2026 → 4 ene 2027 (6 noches)
A3: Días para el viaje | B3: =Cabaña!B2-TODAY()
A4: Costo total cabaña | B4: =Cabaña!B5
A5: Total gastos variables registrados | B5: =Gastos!$E$102
A6: GRAN TOTAL VIAJE | B6: =Cabaña!B5+Gastos!$E$102
A7: Total abonado por todos | B7: =Abonos!$E$62
A8: Saldo pendiente por recaudar | B8: =(Cabaña!B5+Gastos!$E$102)-Abonos!$E$62
A9: Costo promedio por persona (12 base) | B9: =(Cabaña!B5+Gastos!$E$102)/12
A10: Fecha límite de pago cabaña | B10: =Cabaña!B7
A12: Ver detalle de quién debe / quién va al día en la hoja 'Balance'.

Sheet Cabaña
A1: 🏖️ CABAÑA - COVEÑAS
A2: Fecha de entrada | B2: 46385
A3: Fecha de salida | B3: 46391
A4: Noches | B4: =B3-B2
A5: Costo total cabaña | B5: 6860000
A6: Abono ya pagado (reserva) | B6: =SUMIF(Abonos!D:D,"*reserva*",Abonos!E:E)
A7: Fecha límite de pago | B7: Por confirmar
A8: Costo por noche (base 12 pers.) | B8: =B5/B4
A9: Personas base incluidas | B9: 12
A10: Estado | B10: Reservada ✅ (cabaña #2, Condominio Victoria Real)
A11: Link reserva (Airbnb) | B11: https://es-l.airbnb.com/rooms/1586967966635694597
A13: Nota: el costo por noche por persona se calcula abajo en 'Personas', repartiendo
A14: el costo total entre las noches reales de cada quien (para los que van fechas distintas).

Sheet Personas
A1: 👨‍👩‍👧‍👦 PERSONAS Y NOCHES
A2: Nombre | B2: Grupo familiar | C2: Noches en cabaña | D2: Participa gastos variables (Sí/No) | E2: Nota
A3: Andrés | B3: Grupo Andrés | C3: 6 | D3: Sí
A4: Diana | B4: Grupo Andrés | C4: 6 | D4: Sí
A5: Thomas | B5: Grupo Andrés | C5: 6 | D5: Sí
A6: Ana Maria Moncada | B6: Grupo Ana | C6: 6 | D6: Sí
A7: Isabella | B7: Grupo Ana | C7: 6 | D7: Sí
A8: Alex HenO | B8: Grupo Alex | C8: 6 | D8: Sí
A9: Alyson | B9: Grupo Alex | C9: 6 | D9: Sí
A10: Sandra Arbelaez | B10: Grupo Sandra | C10: 6 | D10: Sí
A11: Juanjo | B11: Grupo Sandra | C11: 6 | D11: Sí
A12: Daniel Felipe Ortega | B12: Casa Mery | C12: 6 | D12: Sí
A13: Marlen Moncada | B13: Casa Mery | C13: 6 | D13: Sí
A14: Patricia Arbelaez | B14: Grupo Paty | C14: 6 | D14: Sí
A15: Julián | B15: Extra (con Alyson - Grupo Alex) | C15: 3 | D15: Sí | E15: Llega después del 31 dic - AJUSTAR noches reales
A17: Total noches-persona: | C17: =SUM(C3:C15)

Sheet Abonos
A1: 💰 ABONOS / ADELANTOS
A2: Fecha | B2: Nombre | C2: Grupo familiar | D2: Concepto | E2: Valor | F2: Nota
A3: 46244 | B3: Andrés | C3: Grupo Andrés | D3: Abono reserva cabaña | E3: 250000 | F3: Pago inicial para asegurar la cabaña
A4: 46244 | B4: Ana Maria Moncada | C4: Grupo Ana | D4: Abono reserva cabaña | E4: 250000 | F4: Pago inicial para asegurar la cabaña
A62: TOTAL ABONADO: | E62: =SUM(E3:E60)

Sheet Gastos
A1: 🧾 GASTOS DEL VIAJE
A2: Fecha | B2: Quién pagó | C2: Categoría | D2: Descripción | E2: Valor | F2: Nota
A102: TOTAL GASTOS: | E102: =SUM(E3:E100)

Sheet Balance
A1: ⚖️ BALANCE POR PERSONA
A2: Nombre | B2: Grupo familiar | C2: Noches | D2: Costo cabaña (prorrateado) | E2: Parte gastos variables | F2: Total a cargo | G2: Total abonado | H2: Saldo (a favor / debe)
A3: =Personas!A3 | B3: =Personas!B3 | C3: =Personas!C3 | D3: =Personas!C3*(Cabaña!$B$5/Personas!$C$17) | E3: =IF(Personas!D3="Sí",Gastos!$E$102/COUNTIF(Personas!$D$3:$D$15,"Sí"),0) | F3: =D3+E3 | G3: =SUMIF(Abonos!$B$3:$B$60,A3,Abonos!$E$3:$E$60) | H3: =G3-F3
A4: =Personas!A4 | B4: =Personas!B4 | C4: =Personas!C4 | D4: =Personas!C4*(Cabaña!$B$5/Personas!$C$17) | E4: =IF(Personas!D4="Sí",Gastos!$E$102/COUNTIF(Personas!$D$3:$D$15,"Sí"),0) | F4: =D4+E4 | G4: =SUMIF(Abonos!$B$3:$B$60,A4,Abonos!$E$3:$E$60) | H4: =G4-F4
A5: =Personas!A5 | B5: =Personas!B5 | C5: =Personas!C5 | D5: =Personas!C5*(Cabaña!$B$5/Personas!$C$17) | E5: =IF(Personas!D5="Sí",Gastos!$E$102/COUNTIF(Personas!$D$3:$D$15,"Sí"),0) | F5: =D5+E5 | G5: =SUMIF(Abonos!$B$3:$B$60,A5,Abonos!$E$3:$E$60) | H5: =G5-F5
A6: =Personas!A6 | B6: =Personas!B6 | C6: =Personas!C6 | D6: =Personas!C6*(Cabaña!$B$5/Personas!$C$17) | E6: =IF(Personas!D6="Sí",Gastos!$E$102/COUNTIF(Personas!$D$3:$D$15,"Sí"),0) | F6: =D6+E6 | G6: =SUMIF(Abonos!$B$3:$B$60,A6,Abonos!$E$3:$E$60) | H6: =G6-F6
A7: =Personas!A7 | B7: =Personas!B7 | C7: =Personas!C7 | D7: =Personas!C7*(Cabaña!$B$5/Personas!$C$17) | E7: =IF(Personas!D7="Sí",Gastos!$E$102/COUNTIF(Personas!$D$3:$D$15,"Sí"),0) | F7: =D7+E7 | G7: =SUMIF(Abonos!$B$3:$B$60,A7,Abonos!$E$3:$E$60) | H7: =G7-F7
A8: =Personas!A8 | B8: =Personas!B8 | C8: =Personas!C8 | D8: =Personas!C8*(Cabaña!$B$5/Personas!$C$17) | E8: =IF(Personas!D8="Sí",Gastos!$E$102/COUNTIF(Personas!$D$3:$D$15,"Sí"),0) | F8: =D8+E8 | G8: =SUMIF(Abonos!$B$3:$B$60,A8,Abonos!$E$3:$E$60) | H8: =G8-F8
A9: =Personas!A9 | B9: =Personas!B9 | C9: =Personas!C9 | D9: =Personas!C9*(Cabaña!$B$5/Personas!$C$17) | E9: =IF(Personas!D9="Sí",Gastos!$E$102/COUNTIF(Personas!$D$3:$D$15,"Sí"),0) | F9: =D9+E9 | G9: =SUMIF(Abonos!$B$3:$B$60,A9,Abonos!$E$3:$E$60) | H9: =G9-F9
A10: =Personas!A10 | B10: =Personas!B10 | C10: =Personas!C10 | D10: =Personas!C10*(Cabaña!$B$5/Personas!$C$17) | E10: =IF(Personas!D10="Sí",Gastos!$E$102/COUNTIF(Personas!$D$3:$D$15,"Sí"),0) | F10: =D10+E10 | G10: =SUMIF(Abonos!$B$3:$B$60,A10,Abonos!$E$3:$E$60) | H10: =G10-F10
A11: =Personas!A11 | B11: =Personas!B11 | C11: =Personas!C11 | D11: =Personas!C11*(Cabaña!$B$5/Personas!$C$17) | E11: =IF(Personas!D11="Sí",Gastos!$E$102/COUNTIF(Personas!$D$3:$D$15,"Sí"),0) | F11: =D11+E11 | G11: =SUMIF(Abonos!$B$3:$B$60,A11,Abonos!$E$3:$E$60) | H11: =G11-F11
A12: =Personas!A12 | B12: =Personas!B12 | C12: =Personas!C12 | D12: =Personas!C12*(Cabaña!$B$5/Personas!$C$17) | E12: =IF(Personas!D12="Sí",Gastos!$E$102/COUNTIF(Personas!$D$3:$D$15,"Sí"),0) | F12: =D12+E12 | G12: =SUMIF(Abonos!$B$3:$B$60,A12,Abonos!$E$3:$E$60) | H12: =G12-F12
A13: =Personas!A13 | B13: =Personas!B13 | C13: =Personas!C13 | D13: =Personas!C13*(Cabaña!$B$5/Personas!$C$17) | E13: =IF(Personas!D13="Sí",Gastos!$E$102/COUNTIF(Personas!$D$3:$D$15,"Sí"),0) | F13: =D13+E13 | G13: =SUMIF(Abonos!$B$3:$B$60,A13,Abonos!$E$3:$E$60) | H13: =G13-F13
A14: =Personas!A14 | B14: =Personas!B14 | C14: =Personas!C14 | D14: =Personas!C14*(Cabaña!$B$5/Personas!$C$17) | E14: =IF(Personas!D14="Sí",Gastos!$E$102/COUNTIF(Personas!$D$3:$D$15,"Sí"),0) | F14: =D14+E14 | G14: =SUMIF(Abonos!$B$3:$B$60,A14,Abonos!$E$3:$E$60) | H14: =G14-F14
A15: =Personas!A15 | B15: =Personas!B15 | C15: =Personas!C15 | D15: =Personas!C15*(Cabaña!$B$5/Personas!$C$17) | E15: =IF(Personas!D15="Sí",Gastos!$E$102/COUNTIF(Personas!$D$3:$D$15,"Sí"),0) | F15: =D15+E15 | G15: =SUMIF(Abonos!$B$3:$B$60,A15,Abonos!$E$3:$E$60) | H15: =G15-F15
E17: TOTALES: | F17: =SUM(F3:F15) | G17: =SUM(G3:G15) | H17: =SUM(H3:H15)

Sheet Estimado
A1: 🔮 PRESUPUESTO ESTIMADO (predictivo)
A2: Estimado con base en investigación web (blogs de viaje, foros de peajes, comunidad Tesla Colombia, listados de cabañas). Ajusta los supuestos en amarillo — el resto se recalcula solo.
A4: SUPUESTOS (edítalos)
A5: Personas (comida + ocio playa) | B5: 13
A6: Días del viaje | B6: 6
A7: Número de carros | B7: 3
A8: → de los cuales, a gasolina | B8: 2
A9: → de los cuales, Tesla Model Y RWD | B9: 1
A10: Precio galón gasolina (COP) | B10: 17000
A11: Rendimiento promedio (km/galón) | B11: 35
A12: Distancia Medellín–Coveñas (km, ida) | B12: 500
A13: Peajes ida y vuelta por carro (COP) | B13: 160000
A14: Carga Tesla ida y vuelta (COP, ver hoja Tesla) | B14: =Tesla!C23
A15: Comida por persona/día (COP) | B15: 30000
A16: Señora de servicio por día (COP) | B16: 100000
A17: Ocio diario en playa por persona/día (COP) | B17: 25000
A19: ESTIMADO POR CATEGORÍA
A20: Categoría | B20: Cálculo | C20: Total estimado | D20: Fuente / nota
A21: Alimentación / mercado | B21: =B5*B6*B15 | C21: =B21 | D21: Sin dato específico de Coveñas — estimado con referencia costa Caribe colombiana (autoconsumo, no restaurante)
A22: Transporte — carros a gasolina | B22: =B8*((2*B12/B11*B10)+B13) | C22: =B22 | D22: colombiapeajes.com + tarifas.info: ~493-540km, ~$170-210k gasolina + ~$80k peajes por trayecto
A23: Transporte — Tesla Model Y RWD | B23: =B14 | C23: =B23 | D23: Club Tesla Colombia: Supercargador Medellín $1.300/kWh (~$50k por carga rápida). Asume carga en casa + 1 parada rápida por trayecto; sin Supercargador confirmado en la ruta a Coveñas
A24: Señora de servicio (cocina + aseo) | B24: =B16*B6 | C24: =B24 | D24: Listados de cabañas en Coveñas (Airbnb/Renti): $80k–$110k/día para grupos de hasta 10-12 personas
A25: Ocio diario en playa (toldo/silla, bebidas) | B25: =B5*B6*B17 | C25: =B25 | D25: Sin dato específico de Coveñas — estimado de referencia costa Caribe. No incluye paseo a Islas de San Bernardo (eso va en 'Actividades')
A27: Subtotal estimado (sin cabaña): | C27: =SUM(C21:C25)
A29: GRAN TOTAL ESTIMADO DEL VIAJE
A30: Costo cabaña (real, ya reservada) | C30: =Cabaña!B5
A31: + Subtotal estimado arriba | C31: =C27
A32: =GRAN TOTAL ESTIMADO DEL VIAJE | C32: =C30+C27
A33: ≈ por persona | C33: =C32/B5
A36: Nota: los blogs de viaje (Isatour, Ecoturismo Colombia) reportan viajes de 4 noches desde Medellín (transporte + hospedaje + comida + 2 excursiones) entre $700.000 y $1.200.000 COP por persona. Nuestro estimado por persona para 6 noches queda dentro de un rango razonable frente a esa referencia.

Sheet Tesla
A1: 🔋 TESLA MODEL Y RWD — Medellín → Coveñas
A2: Ruta, paradas de carga, presupuesto y checklist para el carro de Andrés. Investigado en Club Tesla Colombia, guías de viaje en eléctrico a la costa Caribe y foros de carreteras — confirma disponibilidad real antes de salir, la red cambia seguido.
A4: RUTA Y PARADAS DE CARGA
A5: Parada | B5: Km aprox. desde Medellín | C5: Tipo de carga | D5: Nota
A6: Medellín (Unicentro, Laureles) | B6: 0 km | C6: Supercharger Tesla | D6: Cargar al 100% aquí antes de salir. Es el Supercargador Tesla nativo más cercano al origen.
A7: Caucasia | B7: ≈ 250 km | C7: CCS Combo 2 (rápido) | D7: Punto medio natural de la ruta. Requiere adaptador CCS — confirmar con Electromaps/Chargemap que esté operativo antes de salir.
A8: Planeta Rica / Sincelejo | B8: ≈ 350–400 km | C8: CCS Combo 2 (variable) | D8: Alternativa si Caucasia no tiene el cargador disponible. Cobertura menos confiable, llevar margen.
A9: Coveñas / Tolú | B9: ≈ 500 km (destino) | C9: Toma normal 110V (carga lenta) / variable | D9: Confirmar con la propietaria si la cabaña tiene toma disponible para carga lenta overnight — evita depender de la red pública para el regreso.
A11: AUTONOMÍA Y CLIMA
A12: • Model Y RWD: autonomía WLTP menor que la versión Long Range (~600 km) — cuenta con menos rango de sobra.
A13: • En clima cálido (costa) la autonomía real baja entre 10% y 15% frente al valor de ficha, sobre todo usando aire acondicionado.
A14: • La topografía montañosa de la salida de Medellín también reduce el rendimiento — prevé más margen que en terreno plano.
A15: • Con ≈500 km de trayecto y autonomía real probable de 350–400 km, es indispensable al menos 1 parada de carga por trayecto.
A17: PRESUPUESTO DE CARGA (ida y vuelta)
A18: Tramo | B18: Tipo | C18: Estimado | D18: Nota
A19: Carga de salida en Medellín | B19: Supercharger ($1.300/kWh) | C19: 80000 | D19: Completar al 100% antes de salir
A20: Parada Caucasia (ida) | B20: CCS Combo 2, carga parcial | C20: 50000 | D20: Solo lo necesario para llegar a Coveñas
A21: Carga en destino (cabaña) | B21: Toma normal / lenta | C21: 15000 | D21: Si la propietaria confirma toma disponible; tarifa doméstica, mucho más barata
A22: Parada Caucasia (regreso) | B22: CCS Combo 2, carga parcial | C22: 50000 | D22: Para volver a Medellín con margen
A23: Total estimado carga Tesla (ida y vuelta): | C23: =SUM(C19:C22)
A24: Nota: mucho más barato que un carro a gasolina en el mismo trayecto (~$466.000 ida y vuelta en gasolina+peajes, ver hoja 'Estimado'). El supuesto 'Carga Tesla ida y vuelta' de la hoja Estimado está ligado a este total.
A27: CHECKLIST ANTES DE SALIR
A28: ☐ Cargar al 100% en el Supercargador de Unicentro Medellín la noche o mañana antes de salir.
A29: ☐ Llevar el adaptador CCS Combo 2 — la mayoría de cargadores rápidos en Colombia usan ese estándar, no el conector Tesla.
A30: ☐ Instalar Electromaps o Chargemap y confirmar el día del viaje qué cargadores de Caucasia/Sincelejo están operativos.
A31: ☐ Llevar el cable/cargador portátil (mobile connector) por si toca cargar lento en una toma normal.
A32: ☐ Revisión preventiva antes de carretera: llantas, frenos, sistema de refrigeración de batería.
A33: ☐ Activar modo Eco y aprovechar el frenado regenerativo; usar el aire acondicionado a temperatura media, no al máximo.
A34: ☐ No conectar a cargar apenas se llega bajo sol fuerte — dejar que la batería se estabilice unos minutos primero.
A35: ☐ En Coveñas, evitar dejar el carro parqueado directo al sol del mediodía por horas largas.
A36: ☐ Confirmar con la propietaria de la cabaña si hay una toma 110V disponible para cargar lento durante la estadía.
A37: ☐ Tener un plan B (ruta o parada alterna) si algún cargador de la lista aparece fuera de servicio ese día.
... A43: — La República / El Tiempo — mapa de estaciones de carga en Colombia

Sheet Carros
A1: ⛽ CARROS A GASOLINA — Medellín → Coveñas
A2: Ruta, presupuesto y checklist para los 2 carros a gasolina del grupo. Mismos supuestos que la hoja 'Estimado' — investigado en foros de peajes y guías de viaje.
A4: RUTA Y PARADAS
A5: Parada | B5: Km aprox. desde Medellín | C5: Qué hacer ahí | D5: Nota
A6: Medellín | B6: 0 km | C6: Salida | D6: Tanquear lleno antes de salir — evita buscar bomba con poco tiempo.
A7: Santa Fe de Antioquia / Caucasia | B7: ≈ 250 km | C7: Descanso + gasolina | D7: Punto medio natural, hay estaciones de servicio y sitios para comer.
A8: Planeta Rica / Sincelejo | B8: ≈ 350–400 km | C8: Gasolina si hace falta | D8: Segunda opción de tanqueo si no se llenó completo en Caucasia.
A9: Coveñas / Tolú | B9: ≈ 500 km (destino) | C9: Llegada | D9: Confirmar parqueadero disponible en el condominio para los 2 carros.
A11: PRESUPUESTO POR CARRO (ida y vuelta)
A12: Concepto | B12: Cálculo | C12: Estimado | D12: Fuente / nota
A13: Gasolina (ida y vuelta) | B13: ≈500km ida x2 / 35 km-galón x $17.000/galón | C13: 486000 | D13: colombiapeajes.com / tarifas.info — rango real $340k-420k según rendimiento del carro
A14: Peajes (ida y vuelta) | B14: ≈$80.000 por trayecto x2 | C14: 160000 | D14: colombiapeajes.com — ruta Medellín-Coveñas
A15: Total estimado por carro (ida y vuelta): | C15: =SUM(C13:C14)
A16: Total 2 carros a gasolina: | C16: =C15*2
A18: CHECKLIST ANTES DE SALIR
A19: ☐ Revisión preventiva: llantas (incluida la de repuesto), frenos, aceite, luces, batería.
A20: ☐ SOAT y tecnomecánica vigentes para la fecha del viaje.
A21: ☐ Kit de carretera: gato, cruceta, triángulos, chaleco reflectivo, botiquín, extintor.
A22: ☐ Tanquear lleno en Medellín antes de salir — no todas las paradas intermedias tienen bomba confiable.
A23: ☐ Coordinar con el otro carro un punto de encuentro fijo si se separan en el camino.
A24: ☐ Llevar efectivo para peajes (algunos puntos de la ruta no tienen pago electrónico).
A25: ☐ Descansar cada 2-3 horas de manejo — son cerca de 9 horas de carretera.
A26: ☐ Guardar el recibo/soporte de gasolina y peajes si se va a repartir el gasto entre el carro.
A28: FUENTES CONSULTADAS
A29: — colombiapeajes.com — peajes ruta Medellín-Coveñas
A30: — tarifas.info — gasolina y peajes Medellín-Coveñas 2025
A31: — yotellevo.net / himmera.com — distancia y tiempo de viaje Medellín-Coveñas
